{"frames": {

"coarse_dirt.png":
{
	"frame": {"x":1,"y":1,"w":32,"h":32},
	"rotated": false,
	"trimmed": false,
	"spriteSourceSize": {"x":0,"y":0,"w":32,"h":32},
	"sourceSize": {"w":32,"h":32}
},
"cobblestone.png":
{
	"frame": {"x":34,"y":1,"w":32,"h":32},
	"rotated": false,
	"trimmed": false,
	"spriteSourceSize": {"x":0,"y":0,"w":32,"h":32},
	"sourceSize": {"w":32,"h":32}
},
"debug.png":
{
	"frame": {"x":67,"y":1,"w":32,"h":32},
	"rotated": false,
	"trimmed": false,
	"spriteSourceSize": {"x":0,"y":0,"w":32,"h":32},
	"sourceSize": {"w":32,"h":32}
},
"debug2.png":
{
	"frame": {"x":1,"y":34,"w":32,"h":32},
	"rotated": false,
	"trimmed": false,
	"spriteSourceSize": {"x":0,"y":0,"w":32,"h":32},
	"sourceSize": {"w":32,"h":32}
},
"dirt.png":
{
	"frame": {"x":34,"y":34,"w":32,"h":32},
	"rotated": false,
	"trimmed": false,
	"spriteSourceSize": {"x":0,"y":0,"w":32,"h":32},
	"sourceSize": {"w":32,"h":32}
},
"grass.png":
{
	"frame": {"x":67,"y":34,"w":32,"h":32},
	"rotated": false,
	"trimmed": false,
	"spriteSourceSize": {"x":0,"y":0,"w":32,"h":32},
	"sourceSize": {"w":32,"h":32}
},
"grass_block_side.png":
{
	"frame": {"x":1,"y":67,"w":32,"h":32},
	"rotated": false,
	"trimmed": false,
	"spriteSourceSize": {"x":0,"y":0,"w":32,"h":32},
	"sourceSize": {"w":32,"h":32}
},
"grass_block_side_overlay.png":
{
	"frame": {"x":34,"y":67,"w":32,"h":32},
	"rotated": false,
	"trimmed": false,
	"spriteSourceSize": {"x":0,"y":0,"w":32,"h":32},
	"sourceSize": {"w":32,"h":32}
},
"grass_block_snow.png":
{
	"frame": {"x":67,"y":67,"w":32,"h":32},
	"rotated": false,
	"trimmed": false,
	"spriteSourceSize": {"x":0,"y":0,"w":32,"h":32},
	"sourceSize": {"w":32,"h":32}
},
"grass_block_top.png":
{
	"frame": {"x":1,"y":100,"w":32,"h":32},
	"rotated": false,
	"trimmed": false,
	"spriteSourceSize": {"x":0,"y":0,"w":32,"h":32},
	"sourceSize": {"w":32,"h":32}
},
"sand.png":
{
	"frame": {"x":34,"y":100,"w":32,"h":32},
	"rotated": false,
	"trimmed": false,
	"spriteSourceSize": {"x":0,"y":0,"w":32,"h":32},
	"sourceSize": {"w":32,"h":32}
},
"stone.png":
{
	"frame": {"x":67,"y":100,"w":32,"h":32},
	"rotated": false,
	"trimmed": false,
	"spriteSourceSize": {"x":0,"y":0,"w":32,"h":32},
	"sourceSize": {"w":32,"h":32}
}},
"meta": {
	"app": "https://www.codeandweb.com/texturepacker",
	"version": "1.0",
	"image": "spritesheet.png",
	"format": "RGBA8888",
	"size": {"w":100,"h":133},
	"scale": "1",
	"smartupdate": "$TexturePacker:SmartUpdate:594ed5dbc0cb90a3117f8468f60e7c25:d047f1af7132b7dd61a1efbd1b26dc07:729adc6043343cfda41c447ce8f464d6$"
}
}
